app.py
controller.py
imageresource.py
processing/__init__.py
processing/backgroundextractor.py
processing/backgroundsubtractor.py
processing/cloudclipper.py
processing/clusterer.py
processing/dataentities.py
processing/framestream.py
processing/lidarprocessor.py
processing/outputwritter.py
processing/pcapframeparser.py
processing/planetranformer.py
processing/tracker.py
ui/__init__.py
ui/backgrounddock.py
ui/clippingdockui.py
ui/clusteringdock.py
ui/gltextitem.py
ui/iconresource_rc.py
ui/inputdialog.py
ui/lidargraphicsview.py
ui/outputdialog.py
ui/trackingdock.py
ui/transformdockui.py
ui/uithread.py
ui/xytable.py
pylidartracker-1.0.5.dist-info/METADATA
pylidartracker-1.0.5.dist-info/WHEEL
pylidartracker-1.0.5.dist-info/entry_points.txt
pylidartracker-1.0.5.dist-info/top_level.txt
pylidartracker-1.0.5.dist-info/RECORD
